<xml xmlns:o="urn:schemas-microsoft-com:office:office">
 <o:File HRef="minimize.gif"/>
 <o:File HRef="maximize.gif"/>
 <o:File HRef="go.gif"/>
 <o:File HRef="fullpage.gif"/>
 <o:File HRef="plus.gif"/>
 <o:File HRef="minus.gif"/>
 <o:File HRef="panminus.gif"/>
 <o:File HRef="panplus.gif"/>
 <o:File HRef="tick-foc.gif"/>
 <o:File HRef="tick-off.gif"/>
 <o:File HRef="tick-on.gif"/>
 <o:File HRef="toc.gif"/>
 <o:File HRef="toc2.gif"/>
 <o:File HRef="arrow.png"/>
 <o:File HRef="data.xml"/>
 <o:File HRef="frameset.js"/>
 <o:File HRef="keys.js"/>
 <o:File HRef="visio.css"/>
 <o:File HRef="3DCDE61C-0B48-4C1D-9F46-391BD56A2F23.png"/>
 <o:File HRef="5F91C39F-79B0-4437-9C12-794408CBC369.png"/>
 <o:File HRef="380D41B6-D8E3-4A50-9B05-6C443F2BDFDD.png"/>
 <o:File HRef="D27442E8-B247-46F2-906F-3C7520C2EE33.png"/>
 <o:File HRef="xaml_1.xaml"/>
 <o:File HRef="png_1.png"/>
 <o:File HRef="xaml_1.js"/>
 <o:File HRef="Silverlight.js"/>
 <o:File HRef="Silverlight.supportedUserAgent.js"/>
 <o:File HRef="xaml_1.htm"/>
 <o:File HRef="png_1.js"/>
 <o:File HRef="png_1.htm"/>
 <o:File HRef="xaml_2.xaml"/>
 <o:File HRef="png_2.png"/>
 <o:File HRef="xaml_2.htm"/>
 <o:File HRef="png_2.htm"/>
 <o:File HRef="4E68036B-3212-0262-F903-543AD06DE777.odttf"/>
 <o:File HRef="5D173371-4E48-6778-0D70-924A294C1D0A.odttf"/>
 <o:File HRef="3B296586-4B99-4B72-DB48-74681C56FA2B.odttf"/>
 <o:File HRef="zoom.htm"/>
 <o:File HRef="find.js"/>
 <o:File HRef="widgets.htm"/>
 <o:File HRef="toolbar.htm"/>
 <o:MainFile HRef="../Visio.htm"/>
 <o:File HRef="filelist.xml"/>
</xml>